porf/__init__.py
porf/open_sta_parser.py
porf/run_analyser.py
porf-0.0.6.dist-info/LICENSE
porf-0.0.6.dist-info/METADATA
porf-0.0.6.dist-info/WHEEL
porf-0.0.6.dist-info/top_level.txt
porf-0.0.6.dist-info/RECORD
